custum_style_src/material-polyfills/package-lock.json
custum_style_src/material-polyfills/package.json
custum_style_src/material-polyfills/tsconfig.json
custum_style_src/material-polyfills/webpack.config.ts
custum_style_src/material-polyfills/dev-site/index.html
custum_style_src/material-polyfills/dev-site/assets/creating-your-site.png
custum_style_src/material-polyfills/dev-site/assets/search-highlighting.png
custum_style_src/material-polyfills/dev-site/assets/css/extra.css
custum_style_src/material-polyfills/dev-site/assets/stylesheets/main.4dd2dd8d.min.css
custum_style_src/material-polyfills/dev-site/assets/stylesheets/main.4dd2dd8d.min.css.map
custum_style_src/material-polyfills/dev-site/assets/stylesheets/overrides.2b41d529.min.css
custum_style_src/material-polyfills/dev-site/assets/stylesheets/overrides.2b41d529.min.css.map
custum_style_src/material-polyfills/dev-site/assets/stylesheets/palette.6a5ad368.min.css
custum_style_src/material-polyfills/dev-site/assets/stylesheets/palette.6a5ad368.min.css.map
custum_style_src/material-polyfills/src/javascripts/index.ts
custum_style_src/material-polyfills/src/javascripts/converter/twemoji.ts
custum_style_src/material-polyfills/src/stylesheets/_config.scss
custum_style_src/material-polyfills/src/stylesheets/polyfills.scss
custum_style_src/material-polyfills/src/stylesheets/extensions/_admonition.scss
custum_style_src/material-polyfills/src/stylesheets/extensions/_footnotes.scss
custum_style_src/material-polyfills/src/stylesheets/extensions/pymdown/_details.scss
custum_style_src/material-polyfills/src/stylesheets/extensions/pymdown/_tasklist.scss
custum_style_src/material-polyfills/src/stylesheets/main/_typeset.scss
custum_style_src/material-polyfills/src/stylesheets/utilities/_convert.scss
custum_style_src/material-polyfills/typings/webpack-modules.d.ts
docker/mkdocs-with-pdf/README.md
docker/mkdocs-with-pdf/docker-compose.yml
docker/mkdocs-with-pdf/alpine/Dockerfile
mkdocs_with_pdf_browser-1.1.3.dist-info/LICENSE
mkdocs_with_pdf_browser-1.1.3.dist-info/METADATA
mkdocs_with_pdf_browser-1.1.3.dist-info/WHEEL
mkdocs_with_pdf_browser-1.1.3.dist-info/entry_points.txt
mkdocs_with_pdf_browser-1.1.3.dist-info/top_level.txt
mkdocs_with_pdf_browser-1.1.3.dist-info/RECORD
