Metadata-Version: 2.1
Name: mkdocs-with-pdf-browser
Version: 1.1.3
Summary: Generate a single PDF file from MkDocs repository, a fork of the original project mkdocs-with-pdf but witout the weasyprint dependency dependency
Author-email: carneirofc <claudiofcarneiro@hotmail.com>
License: MIT
Project-URL: homepage, https://github.com/carneirofc/mkdocs-with-pdf
Keywords: mkdocs,backstage,pdf,chrome,mkdocs-with-pdf,nightly
Classifier: Development Status :: 4 - Beta
Classifier: Intended Audience :: Developers
Classifier: Intended Audience :: Information Technology
Classifier: License :: OSI Approved :: MIT License
Classifier: Programming Language :: Python
Classifier: Programming Language :: Python :: 3 :: Only
Classifier: Programming Language :: Python :: 3.12
Requires-Python: >=3.12
License-File: LICENSE
Requires-Dist: mkdocs>=1.1
Requires-Dist: beautifulsoup4>=4.6.3
Requires-Dist: libsass>=0.15
Requires-Dist: playwright>=1.46.0
